main.py
config/__init__.py
core/__init__.py
core/arg_parser.py
core/validator.py
models/__init__.py
models/object_set.py
models/result.py
models/schema.py
samples/__init__.py
tests/__init__.py
tests/test_doc_validation.py
tests/test_schema_validation.py
tests/test_util.py
utils/__init__.py
utils/logger.py
utils/message_list.py
utils/util.py
validations/__init__.py
validations/doc_validations.py
validations/schema_validations.py
validations/validation.py
jsvl-1.0.3.dist-info/LICENSE
jsvl-1.0.3.dist-info/METADATA
jsvl-1.0.3.dist-info/WHEEL
jsvl-1.0.3.dist-info/entry_points.txt
jsvl-1.0.3.dist-info/top_level.txt
jsvl-1.0.3.dist-info/RECORD
